flore1/__init__.py
flore1/engine_locals/__init__.py
flore1/engine_locals/flipbook.py
flore1/engine_locals/gameFilesHandler.py
flore1/engine_locals/inputHandler.py
flore1/engine_locals/pictureConverter.py
flore1/engine_locals/refresh.py
flore1/engine_locals/scene.py
flore1/engine_locals/textAsset.py
flore1/engine_locals/textSprite.py
flore1/engine_locals/util_functions.py
flore1/engine_locals/engine_assets_lib/logo.png
flore1/engine_locals/engine_consts/__init__.py
flore1/engine_locals/engine_consts/ansiRGB.py
flore1-1.5.3.dist-info/LICENSE
flore1-1.5.3.dist-info/METADATA
flore1-1.5.3.dist-info/WHEEL
flore1-1.5.3.dist-info/top_level.txt
flore1-1.5.3.dist-info/RECORD
